{"data":[{"codparticipant":40910826,"jugador":"ERIK","dorsal":9,"any":2010,"codequip":37822,"nom_equip":"DAMM, C.F. B","escut":"00100_0000672082_damm_200x200.png","minut":34,"jornada":1,"tipus":"normal"},{"codparticipant":25911697,"jugador":"ADRIAN","dorsal":14,"any":2010,"codequip":37822,"nom_equip":"DAMM, C.F. B","escut":"00100_0000672082_damm_200x200.png","minut":62,"jornada":1,"tipus":"normal"},{"codparticipant":40910826,"jugador":"ERIK","dorsal":9,"any":2010,"codequip":37822,"nom_equip":"DAMM, C.F. B","escut":"00100_0000672082_damm_200x200.png","minut":68,"jornada":1,"tipus":"normal"},{"codparticipant":40910826,"jugador":"ERIK","dorsal":9,"any":2010,"codequip":37822,"nom_equip":"DAMM, C.F. B","escut":"00100_0000672082_damm_200x200.png","minut":53,"jornada":2,"tipus":"normal"},{"codparticipant":30114686,"jugador":"TRISTAN","dorsal":7,"any":2010,"codequip":37822,"nom_equip":"DAMM, C.F. B","escut":"00100_0000672082_damm_200x200.png","minut":34,"jornada":3,"tipus":"normal"},{"codparticipant":29695037,"jugador":"MARTIN","dorsal":4,"any":2010,"codequip":37822,"nom_equip":"DAMM, C.F. B","escut":"00100_0000672082_damm_200x200.png","minut":32,"jornada":6,"tipus":"normal"},{"codparticipant":30114686,"jugador":"TRISTAN","dorsal":12,"any":2010,"codequip":37822,"nom_equip":"DAMM, C.F. B","escut":"00100_0000672082_damm_200x200.png","minut":68,"jornada":6,"tipus":"normal"},{"codparticipant":30114686,"jugador":"TRISTAN","dorsal":17,"any":2010,"codequip":37822,"nom_equip":"DAMM, C.F. B","escut":"00100_0000672082_damm_200x200.png","minut":51,"jornada":9,"tipus":"normal"},{"codparticipant":29695037,"jugador":"MARTIN","dorsal":4,"any":2010,"codequip":37822,"nom_equip":"DAMM, C.F. B","escut":"00100_0000672082_damm_200x200.png","minut":11,"jornada":11,"tipus":"normal"},{"codparticipant":40910826,"jugador":"ERIK","dorsal":9,"any":2010,"codequip":37822,"nom_equip":"DAMM, C.F. B","escut":"00100_0000672082_damm_200x200.png","minut":24,"jornada":11,"tipus":"penalti"},{"codparticipant":40910969,"jugador":"ERIK","dorsal":11,"any":2010,"codequip":37822,"nom_equip":"DAMM, C.F. B","escut":"00100_0000672082_damm_200x200.png","minut":69,"jornada":11,"tipus":"normal"},{"codparticipant":30114686,"jugador":"TRISTAN","dorsal":11,"any":2010,"codequip":37822,"nom_equip":"DAMM, C.F. B","escut":"00100_0000672082_damm_200x200.png","minut":13,"jornada":12,"tipus":"normal"},{"codparticipant":40910826,"jugador":"ERIK","dorsal":9,"any":2010,"codequip":37822,"nom_equip":"DAMM, C.F. B","escut":"00100_0000672082_damm_200x200.png","minut":69,"jornada":12,"tipus":"penalti"},{"codparticipant":24328821,"jugador":"DARIO","dorsal":4,"any":2010,"codequip":37822,"nom_equip":"DAMM, C.F. B","escut":"00100_0000672082_damm_200x200.png","minut":10,"jornada":13,"tipus":"normal"},{"codparticipant":30114686,"jugador":"TRISTAN","dorsal":15,"any":2010,"codequip":37822,"nom_equip":"DAMM, C.F. B","escut":"00100_0000672082_damm_200x200.png","minut":55,"jornada":13,"tipus":"normal"},{"codparticipant":40910969,"jugador":"ERIK","dorsal":7,"any":2010,"codequip":37822,"nom_equip":"DAMM, C.F. B","escut":"00100_0000672082_damm_200x200.png","minut":61,"jornada":13,"tipus":"normal"},{"codparticipant":26837437,"jugador":"MAX","dorsal":14,"any":2010,"codequip":37822,"nom_equip":"DAMM, C.F. B","escut":"00100_0000672082_damm_200x200.png","minut":67,"jornada":14,"tipus":"normal"},{"codparticipant":20919050,"jugador":"PERE","dorsal":8,"any":2010,"codequip":37822,"nom_equip":"DAMM, C.F. B","escut":"00100_0000672082_damm_200x200.png","minut":3,"jornada":15,"tipus":"normal"},{"codparticipant":40910969,"jugador":"ERIK","dorsal":7,"any":2010,"codequip":37822,"nom_equip":"DAMM, C.F. B","escut":"00100_0000672082_damm_200x200.png","minut":45,"jornada":15,"tipus":"normal"},{"codparticipant":26113203,"jugador":"RICARD","dorsal":11,"any":2010,"codequip":37822,"nom_equip":"DAMM, C.F. B","escut":"00100_0000672082_damm_200x200.png","minut":2,"jornada":17,"tipus":"normal"},{"codparticipant":27555626,"jugador":"BANNA","dorsal":3,"any":2010,"codequip":37822,"nom_equip":"DAMM, C.F. B","escut":"00100_0000672082_damm_200x200.png","minut":50,"jornada":17,"tipus":"normal"},{"codparticipant":27555626,"jugador":"BANNA","dorsal":11,"any":2010,"codequip":37822,"nom_equip":"DAMM, C.F. B","escut":"00100_0000672082_damm_200x200.png","minut":24,"jornada":19,"tipus":"normal"},{"codparticipant":30114686,"jugador":"TRISTAN","dorsal":15,"any":2010,"codequip":37822,"nom_equip":"DAMM, C.F. B","escut":"00100_0000672082_damm_200x200.png","minut":48,"jornada":23,"tipus":"normal"},{"codparticipant":26113203,"jugador":"RICARD","dorsal":10,"any":2010,"codequip":37822,"nom_equip":"DAMM, C.F. B","escut":"00100_0000672082_damm_200x200.png","minut":8,"jornada":24,"tipus":"normal"},{"codparticipant":26113203,"jugador":"RICARD","dorsal":10,"any":2010,"codequip":37822,"nom_equip":"DAMM, C.F. B","escut":"00100_0000672082_damm_200x200.png","minut":41,"jornada":25,"tipus":"normal"},{"codparticipant":30114686,"jugador":"TRISTAN","dorsal":11,"any":2010,"codequip":37822,"nom_equip":"DAMM, C.F. B","escut":"00100_0000672082_damm_200x200.png","minut":21,"jornada":26,"tipus":"normal"},{"codparticipant":29433985,"jugador":"MARIANO","dorsal":4,"any":2010,"codequip":37822,"nom_equip":"DAMM, C.F. B","escut":"00100_0000672082_damm_200x200.png","minut":25,"jornada":26,"tipus":"normal"},{"codparticipant":30114686,"jugador":"TRISTAN","dorsal":11,"any":2010,"codequip":37822,"nom_equip":"DAMM, C.F. B","escut":"00100_0000672082_damm_200x200.png","minut":37,"jornada":26,"tipus":"normal"},{"codparticipant":30114686,"jugador":"TRISTAN","dorsal":11,"any":2010,"codequip":37822,"nom_equip":"DAMM, C.F. B","escut":"00100_0000672082_damm_200x200.png","minut":65,"jornada":30,"tipus":"normal"}],"codequip":"37822","codgroup":"44295683","menuFollowTeams":[{"label":"Infantil A","href":"/classificacio?id=44295683"},{"label":"Infantil B","href":"/classificacio?id=45060446"},{"label":"Infantil C","href":"/classificacio?id=45056116"},{"label":"Infantil D","href":"/classificacio?id=45061389"}]}