{"data":{"INFO":{"CODGRUPO":"45056116","GOLES_CASA":"1","GOLES_FUERA":"7","PENALTIS_CASA":null,"PENALTIS_FUERA":null,"CODACTA":"3048125","COD_COMPETICION":43980445,"NOM_COMPETICION":"INFANTIL SEGONA DIVISIÓ","NOM_COMPETICION_URL":"infantil-segona-divisio","COD_GRUPO":45056116,"GRUPO":"GRUP 19","GRUPO_URL":"grup-19","CODEQUIPO_CASA":"36480387","CODEQUIPO_FUERA":"33923","JORNADA":"18","CODIGO_CAMPO":"70","COMIENZO1":"2023-03-04 14:30:00","SUSPENDIDO":"1","NOMBRE":"CAMP DE FUTBOL CEM LA GUINEUETA","DIRECCION":"c/ del Castor, 1","TEMP_NOMBRE":"2223","TEMP_LARGO":"TEMPORADA 2022-2023","CIUDAD":"Barcelona","ESTADO":"4"},"ARBITROS":[{"CODTIPO_ARBITRO":"1","CODARBITRO":"3257384","NOMBRE_ARBITRO":"MIGUEL","NOMBRE":"Barcelona3"}],"GOLES":[{"NOMBRE":"BILAL","LICENCIA":"17","DORSAL":"6","CODPARTICIPANTE":"38984499","FECHA_NACIMIENTO":1,"PORTERO":null,"TIPO":"normal","MINUTO":"45","EQUIPO":"visitante"},{"NOMBRE":"BILAL","LICENCIA":"17","DORSAL":"6","CODPARTICIPANTE":"38984499","FECHA_NACIMIENTO":1,"PORTERO":null,"TIPO":"normal","MINUTO":"55","EQUIPO":"visitante"},{"NOMBRE":"BILAL","LICENCIA":"17","DORSAL":"6","CODPARTICIPANTE":"38984499","FECHA_NACIMIENTO":1,"PORTERO":null,"TIPO":"normal","MINUTO":"63","EQUIPO":"visitante"},{"NOMBRE":"JORDI DAVID","LICENCIA":"17","DORSAL":"8","CODPARTICIPANTE":"45344723","FECHA_NACIMIENTO":1,"PORTERO":null,"TIPO":"normal","MINUTO":"40","EQUIPO":"visitante"},{"NOMBRE":"JORDI DAVID","LICENCIA":"17","DORSAL":"8","CODPARTICIPANTE":"45344723","FECHA_NACIMIENTO":1,"PORTERO":null,"TIPO":"normal","MINUTO":"49","EQUIPO":"visitante"},{"NOMBRE":"EDUARD","LICENCIA":"17","DORSAL":"17","CODPARTICIPANTE":"30905945","FECHA_NACIMIENTO":1,"PORTERO":null,"TIPO":"normal","MINUTO":"27","EQUIPO":"visitante"},{"NOMBRE":"CARLOS DAVID","LICENCIA":"17","DORSAL":"18","CODPARTICIPANTE":"42081968","FECHA_NACIMIENTO":1,"PORTERO":null,"TIPO":"normal","MINUTO":"23","EQUIPO":"visitante"},{"NOMBRE":"NIL","LICENCIA":"17","DORSAL":"42","CODPARTICIPANTE":"45874607","FECHA_NACIMIENTO":2,"PORTERO":null,"TIPO":"normal","MINUTO":"37","EQUIPO":"local"}],"EQUIPO_CASA":{"CODCLUB":6390,"CODCLUB2":6390,"CODEQUIPO":36480387,"NOMBRE_CLUB":"ESCOLA ESPORTIVA GUINEUETA C.F","NOMBRE_CLUB_URL":"escola-esportiva-guineueta-cf","NOMBRE_EQUIPO":"ESCOLA ESPORTIVA GUINEUETA C.F C","NOMBRE_EQUIPO_URL":"escola-esportiva-guineueta-cf-c","NOMBRE":"00100_0000663994_guineueta_200x200.png","NOMBRE_ABREVIADO_URL":"2i","CODGRUPO":41781890,"TITULARES":[{"NOMBRE":"VICTOR","LICENCIA":"17","DORSAL":"6","CODPARTICIPANTE":"46555988","FECHA_NACIMIENTO":1,"PORTERO":null},{"NOMBRE":"HUGO","LICENCIA":"17","DORSAL":"13","CODPARTICIPANTE":"45874727","FECHA_NACIMIENTO":2,"PORTERO":1},{"NOMBRE":"FRANCISCO PEDRO","LICENCIA":"17","DORSAL":"36","CODPARTICIPANTE":"23484527","FECHA_NACIMIENTO":1,"PORTERO":null},{"NOMBRE":"POL","LICENCIA":"17","DORSAL":"40","CODPARTICIPANTE":"26692528","FECHA_NACIMIENTO":1,"PORTERO":null},{"NOMBRE":"GERARD","LICENCIA":"17","DORSAL":"41","CODPARTICIPANTE":"45759236","FECHA_NACIMIENTO":2,"PORTERO":null},{"NOMBRE":"FRANCESC","LICENCIA":"17","DORSAL":"43","CODPARTICIPANTE":"38584649","FECHA_NACIMIENTO":2,"PORTERO":null},{"NOMBRE":"YORMAN AARON","LICENCIA":"17","DORSAL":"44","CODPARTICIPANTE":"42104788","FECHA_NACIMIENTO":2,"PORTERO":null},{"NOMBRE":"DAMIAN","LICENCIA":"17","DORSAL":"46","CODPARTICIPANTE":"34058231","FECHA_NACIMIENTO":1,"PORTERO":null},{"NOMBRE":"ERIC","LICENCIA":"17","DORSAL":"48","CODPARTICIPANTE":"45310750","FECHA_NACIMIENTO":1,"PORTERO":null},{"NOMBRE":"MARTI","LICENCIA":"17","DORSAL":"54","CODPARTICIPANTE":"45265889","FECHA_NACIMIENTO":2,"PORTERO":null},{"NOMBRE":"JOHN","LICENCIA":"17","DORSAL":"60","CODPARTICIPANTE":"37263359","FECHA_NACIMIENTO":2,"PORTERO":null}],"SUPLENTES":[{"NOMBRE":"ANDERSON ARTURO","LICENCIA":"17","DORSAL":"23","CODPARTICIPANTE":"46235023","FECHA_NACIMIENTO":1,"PORTERO":null},{"NOMBRE":"NIL","LICENCIA":"17","DORSAL":"42","CODPARTICIPANTE":"45874607","FECHA_NACIMIENTO":2,"PORTERO":null}],"COSTECNIC":{"Delegat":"ADRIA"},"SUSTITUCIONES":[],"SANCIONES":[]},"EQUIPO_FUERA":{"CODCLUB":1084,"CODCLUB2":1084,"CODEQUIPO":33923,"NOMBRE_CLUB":"MONTAÑESA, C.F.","NOMBRE_CLUB_URL":"montanesa-cf","NOMBRE_EQUIPO":"MONTAÑESA, C.F. C","NOMBRE_EQUIPO_URL":"montanesa-cf-c","NOMBRE":"00100_0000584781_montanesa_200x200.png","NOMBRE_ABREVIADO_URL":"2i","CODGRUPO":41818598,"TITULARES":[{"NOMBRE":"MARIO MAXIMILIANO","LICENCIA":"17","DORSAL":"1","CODPARTICIPANTE":"24266291","FECHA_NACIMIENTO":1,"PORTERO":1},{"NOMBRE":"OMAR","LICENCIA":"17","DORSAL":"2","CODPARTICIPANTE":"33753279","FECHA_NACIMIENTO":2,"PORTERO":null},{"NOMBRE":"MARCOS","LICENCIA":"17","DORSAL":"3","CODPARTICIPANTE":"42378774","FECHA_NACIMIENTO":2,"PORTERO":null},{"NOMBRE":"KEVIN","LICENCIA":"17","DORSAL":"4","CODPARTICIPANTE":"44631450","FECHA_NACIMIENTO":2,"PORTERO":null},{"NOMBRE":"BILAL","LICENCIA":"17","DORSAL":"6","CODPARTICIPANTE":"38984499","FECHA_NACIMIENTO":1,"PORTERO":null},{"NOMBRE":"HARON","LICENCIA":"17","DORSAL":"7","CODPARTICIPANTE":"34260556","FECHA_NACIMIENTO":2,"PORTERO":null},{"NOMBRE":"GERARD","LICENCIA":"17","DORSAL":"11","CODPARTICIPANTE":"45855971","FECHA_NACIMIENTO":2,"PORTERO":null},{"NOMBRE":"ADAM","LICENCIA":"17","DORSAL":"14","CODPARTICIPANTE":"27264146","FECHA_NACIMIENTO":1,"PORTERO":null},{"NOMBRE":"EDUARD","LICENCIA":"17","DORSAL":"17","CODPARTICIPANTE":"30905945","FECHA_NACIMIENTO":1,"PORTERO":null},{"NOMBRE":"CARLOS DAVID","LICENCIA":"17","DORSAL":"18","CODPARTICIPANTE":"42081968","FECHA_NACIMIENTO":1,"PORTERO":null},{"NOMBRE":"AITOR","LICENCIA":"17","DORSAL":"20","CODPARTICIPANTE":"46347528","FECHA_NACIMIENTO":2,"PORTERO":null}],"SUPLENTES":[{"NOMBRE":"JORDI DAVID","LICENCIA":"17","DORSAL":"8","CODPARTICIPANTE":"45344723","FECHA_NACIMIENTO":1,"PORTERO":null},{"NOMBRE":"NABIL","LICENCIA":"17","DORSAL":"12","CODPARTICIPANTE":"38984185","FECHA_NACIMIENTO":2,"PORTERO":null},{"NOMBRE":"LUCAS","LICENCIA":"17","DORSAL":"13","CODPARTICIPANTE":"46243020","FECHA_NACIMIENTO":2,"PORTERO":1},{"NOMBRE":"DAREK DANIEL","LICENCIA":"17","DORSAL":"15","CODPARTICIPANTE":"37351210","FECHA_NACIMIENTO":2,"PORTERO":null},{"NOMBRE":"SANTIAGO","LICENCIA":"17","DORSAL":"16","CODPARTICIPANTE":"43718576","FECHA_NACIMIENTO":2,"PORTERO":null},{"NOMBRE":"ERIC","LICENCIA":"17","DORSAL":"19","CODPARTICIPANTE":"38396532","FECHA_NACIMIENTO":2,"PORTERO":null}],"COSTECNIC":{"Entrenador Titular":"BENITO"},"SUSTITUCIONES":[],"SANCIONES":[{"NOMBRE":"ERIC","LICENCIA":"17","DORSAL":"19","CODPARTICIPANTE":"38396532","FECHA_NACIMIENTO":2,"PORTERO":null,"TIPO":"groga","MINUTO":"25"}]}},"codacta":"3048125","titulars_local":[{"codparticipant":46555988,"codequip":36480387,"dorsal":6,"titularitats":1,"porter":null,"nom":"VICTOR","any":2009,"partits":1,"nom_equip":"ESCOLA ESPORTIVA GUINEUETA C.F C","colorequipacio1":null,"colorequipacio2":null},{"codparticipant":45874727,"codequip":36480387,"dorsal":13,"titularitats":1,"porter":1,"nom":"HUGO","any":2010,"partits":1,"nom_equip":"ESCOLA ESPORTIVA GUINEUETA C.F C","colorequipacio1":null,"colorequipacio2":null},{"codparticipant":46235023,"codequip":36480387,"dorsal":23,"titularitats":0,"porter":null,"nom":"ANDERSON ARTURO","any":2009,"partits":1,"nom_equip":"ESCOLA ESPORTIVA GUINEUETA C.F C","colorequipacio1":null,"colorequipacio2":null},{"codparticipant":23484527,"codequip":36480387,"dorsal":36,"titularitats":1,"porter":null,"nom":"FRANCISCO PEDRO","any":2009,"partits":1,"nom_equip":"ESCOLA ESPORTIVA GUINEUETA C.F C","colorequipacio1":null,"colorequipacio2":null},{"codparticipant":26692528,"codequip":36480387,"dorsal":40,"titularitats":1,"porter":null,"nom":"POL","any":2009,"partits":1,"nom_equip":"ESCOLA ESPORTIVA GUINEUETA C.F C","colorequipacio1":null,"colorequipacio2":null},{"codparticipant":45759236,"codequip":36480387,"dorsal":41,"titularitats":1,"porter":null,"nom":"GERARD","any":2010,"partits":1,"nom_equip":"ESCOLA ESPORTIVA GUINEUETA C.F C","colorequipacio1":null,"colorequipacio2":null},{"codparticipant":45874607,"codequip":36480387,"dorsal":42,"titularitats":0,"porter":null,"nom":"NIL","any":2010,"partits":1,"nom_equip":"ESCOLA ESPORTIVA GUINEUETA C.F C","colorequipacio1":null,"colorequipacio2":null},{"codparticipant":38584649,"codequip":36480387,"dorsal":43,"titularitats":1,"porter":null,"nom":"FRANCESC","any":2010,"partits":1,"nom_equip":"ESCOLA ESPORTIVA GUINEUETA C.F C","colorequipacio1":null,"colorequipacio2":null},{"codparticipant":42104788,"codequip":36480387,"dorsal":44,"titularitats":1,"porter":null,"nom":"YORMAN AARON","any":2010,"partits":1,"nom_equip":"ESCOLA ESPORTIVA GUINEUETA C.F C","colorequipacio1":null,"colorequipacio2":null},{"codparticipant":34058231,"codequip":36480387,"dorsal":46,"titularitats":1,"porter":null,"nom":"DAMIAN","any":2009,"partits":1,"nom_equip":"ESCOLA ESPORTIVA GUINEUETA C.F C","colorequipacio1":null,"colorequipacio2":null},{"codparticipant":45310750,"codequip":36480387,"dorsal":48,"titularitats":1,"porter":null,"nom":"ERIC","any":2009,"partits":1,"nom_equip":"ESCOLA ESPORTIVA GUINEUETA C.F C","colorequipacio1":null,"colorequipacio2":null},{"codparticipant":45265889,"codequip":36480387,"dorsal":54,"titularitats":1,"porter":null,"nom":"MARTI","any":2010,"partits":1,"nom_equip":"ESCOLA ESPORTIVA GUINEUETA C.F C","colorequipacio1":null,"colorequipacio2":null},{"codparticipant":37263359,"codequip":36480387,"dorsal":60,"titularitats":1,"porter":null,"nom":"JOHN","any":2010,"partits":1,"nom_equip":"ESCOLA ESPORTIVA GUINEUETA C.F C","colorequipacio1":null,"colorequipacio2":null}],"titulars_visitant":[{"codparticipant":24266291,"codequip":33923,"dorsal":1,"titularitats":1,"porter":1,"nom":"MARIO MAXIMILIANO","any":2009,"partits":1,"nom_equip":"MONTAÑESA, C.F. C","colorequipacio1":null,"colorequipacio2":null},{"codparticipant":33753279,"codequip":33923,"dorsal":2,"titularitats":1,"porter":null,"nom":"OMAR","any":2010,"partits":1,"nom_equip":"MONTAÑESA, C.F. C","colorequipacio1":null,"colorequipacio2":null},{"codparticipant":42378774,"codequip":33923,"dorsal":3,"titularitats":1,"porter":null,"nom":"MARCOS","any":2010,"partits":1,"nom_equip":"MONTAÑESA, C.F. C","colorequipacio1":null,"colorequipacio2":null},{"codparticipant":44631450,"codequip":33923,"dorsal":4,"titularitats":1,"porter":null,"nom":"KEVIN","any":2010,"partits":1,"nom_equip":"MONTAÑESA, C.F. C","colorequipacio1":null,"colorequipacio2":null},{"codparticipant":38984499,"codequip":33923,"dorsal":6,"titularitats":1,"porter":null,"nom":"BILAL","any":2009,"partits":1,"nom_equip":"MONTAÑESA, C.F. C","colorequipacio1":null,"colorequipacio2":null},{"codparticipant":34260556,"codequip":33923,"dorsal":7,"titularitats":1,"porter":null,"nom":"HARON","any":2010,"partits":1,"nom_equip":"MONTAÑESA, C.F. C","colorequipacio1":null,"colorequipacio2":null},{"codparticipant":45344723,"codequip":33923,"dorsal":8,"titularitats":0,"porter":null,"nom":"JORDI DAVID","any":2009,"partits":1,"nom_equip":"MONTAÑESA, C.F. C","colorequipacio1":null,"colorequipacio2":null},{"codparticipant":45855971,"codequip":33923,"dorsal":11,"titularitats":1,"porter":null,"nom":"GERARD","any":2010,"partits":1,"nom_equip":"MONTAÑESA, C.F. C","colorequipacio1":null,"colorequipacio2":null},{"codparticipant":38984185,"codequip":33923,"dorsal":12,"titularitats":0,"porter":null,"nom":"NABIL","any":2010,"partits":1,"nom_equip":"MONTAÑESA, C.F. C","colorequipacio1":null,"colorequipacio2":null},{"codparticipant":46243020,"codequip":33923,"dorsal":13,"titularitats":0,"porter":1,"nom":"LUCAS","any":2010,"partits":1,"nom_equip":"MONTAÑESA, C.F. C","colorequipacio1":null,"colorequipacio2":null},{"codparticipant":27264146,"codequip":33923,"dorsal":14,"titularitats":1,"porter":null,"nom":"ADAM","any":2009,"partits":1,"nom_equip":"MONTAÑESA, C.F. C","colorequipacio1":null,"colorequipacio2":null},{"codparticipant":37351210,"codequip":33923,"dorsal":15,"titularitats":0,"porter":null,"nom":"DAREK DANIEL","any":2010,"partits":1,"nom_equip":"MONTAÑESA, C.F. C","colorequipacio1":null,"colorequipacio2":null},{"codparticipant":43718576,"codequip":33923,"dorsal":16,"titularitats":0,"porter":null,"nom":"SANTIAGO","any":2010,"partits":1,"nom_equip":"MONTAÑESA, C.F. C","colorequipacio1":null,"colorequipacio2":null},{"codparticipant":30905945,"codequip":33923,"dorsal":17,"titularitats":1,"porter":null,"nom":"EDUARD","any":2009,"partits":1,"nom_equip":"MONTAÑESA, C.F. C","colorequipacio1":null,"colorequipacio2":null},{"codparticipant":42081968,"codequip":33923,"dorsal":18,"titularitats":1,"porter":null,"nom":"CARLOS DAVID","any":2009,"partits":1,"nom_equip":"MONTAÑESA, C.F. C","colorequipacio1":null,"colorequipacio2":null},{"codparticipant":38396532,"codequip":33923,"dorsal":19,"titularitats":0,"porter":null,"nom":"ERIC","any":2010,"partits":1,"nom_equip":"MONTAÑESA, C.F. C","colorequipacio1":null,"colorequipacio2":null},{"codparticipant":46347528,"codequip":33923,"dorsal":20,"titularitats":1,"porter":null,"nom":"AITOR","any":2010,"partits":1,"nom_equip":"MONTAÑESA, C.F. C","colorequipacio1":null,"colorequipacio2":null}],"menuFollowTeams":[{"label":"Infantil A","href":"/classificacio?id=44295683"},{"label":"Infantil B","href":"/classificacio?id=45060446"},{"label":"Infantil C","href":"/classificacio?id=45056116"},{"label":"Infantil D","href":"/classificacio?id=45061389"}]}