{"data":[{"codgroup":45056116,"codequip":39082,"nom":"APA POBLE SEC, CE. A","escut":"00100_0000287980_Escut_2D_-_66px_-_fons_transparent.png","partits":7,"punts":21,"diff_gols":73,"gols_afavor":75,"gols_encontra":2,"posicio":1},{"codgroup":45056116,"codequip":36338,"nom":"CATALÒNIA, U.B. D","escut":"00100_0000675978_catalonia_200x200.png","partits":7,"punts":19,"diff_gols":20,"gols_afavor":29,"gols_encontra":9,"posicio":2},{"codgroup":45056116,"codequip":33281582,"nom":"DIAGONAL CLUB ESP. B","escut":"00100_0000484899_DIAGONAL_CLUB_ESPORTIU_copia.png","partits":7,"punts":16,"diff_gols":28,"gols_afavor":40,"gols_encontra":12,"posicio":3},{"codgroup":45056116,"codequip":25560702,"nom":"ESCOLA DE FUTBOL PREMIER BARCELONA D","escut":"00100_0000754057_premierbcn_200x200.png","partits":6,"punts":15,"diff_gols":27,"gols_afavor":35,"gols_encontra":8,"posicio":4},{"codgroup":45056116,"codequip":37086,"nom":"LLOREDA, C.F. A","escut":"00100_0000897895_cflloreda_200.png","partits":6,"punts":13,"diff_gols":24,"gols_afavor":29,"gols_encontra":5,"posicio":5},{"codgroup":45056116,"codequip":39914,"nom":"SARRIÀ, C.P. C","escut":"00100_0000388904_00100_0000337753_escut-cp-sarria-1952.png","partits":6,"punts":10,"diff_gols":23,"gols_afavor":33,"gols_encontra":10,"posicio":6},{"codgroup":45056116,"codequip":44173252,"nom":"PADUA, ASSOC. CLUB B","escut":"00100_0000813057_6570_Padua_200.png","partits":6,"punts":9,"diff_gols":-9,"gols_afavor":15,"gols_encontra":24,"posicio":7},{"codgroup":45056116,"codequip":40477,"nom":"DON BOSCO, C.F. A","escut":"00100_0000105692_bosco.png","partits":7,"punts":8,"diff_gols":3,"gols_afavor":20,"gols_encontra":17,"posicio":8},{"codgroup":45056116,"codequip":44216155,"nom":"Pª BARC. VILLAVERDE-PENITENTS C","escut":"00100_0000012218_Villaverde pequeno.png","partits":7,"punts":8,"diff_gols":-8,"gols_afavor":18,"gols_encontra":26,"posicio":9},{"codgroup":45056116,"codequip":41973,"nom":"PENYA BARC. COLLBLANC SANTS,AE A","escut":"00100_0000094725_Escudo3_1.png","partits":6,"punts":7,"diff_gols":0,"gols_afavor":16,"gols_encontra":16,"posicio":10},{"codgroup":45056116,"codequip":34252,"nom":"LA SALUT PERE GOL AE. B","escut":"00100_0000651347_lasalutperegol_200x200.png","partits":7,"punts":7,"diff_gols":-20,"gols_afavor":14,"gols_encontra":34,"posicio":11},{"codgroup":45056116,"codequip":34223,"nom":"ESCOLA COLLBLANC-TORRASSA,C.E B","escut":"00100_0000003500_images.png","partits":6,"punts":6,"diff_gols":-3,"gols_afavor":12,"gols_encontra":15,"posicio":12},{"codgroup":45056116,"codequip":33923,"nom":"MONTAÑESA, C.F. C","escut":"00100_0000584781_montanesa_200x200.png","partits":7,"punts":3,"diff_gols":-33,"gols_afavor":10,"gols_encontra":43,"posicio":13},{"codgroup":45056116,"codequip":31737402,"nom":"POBLE NOU ,AT. C","escut":"00100_0000310887_Logo_Facebook.fw.png","partits":0,"punts":0,"diff_gols":0,"gols_afavor":0,"gols_encontra":0,"posicio":14},{"codgroup":45056116,"codequip":40746,"nom":"UNIFICACION LLEFIA,CF. D","escut":"00100_0000879078_llefia_200.png","partits":6,"punts":0,"diff_gols":-36,"gols_afavor":1,"gols_encontra":37,"posicio":15},{"codgroup":45056116,"codequip":36480387,"nom":"ESCOLA ESPORTIVA GUINEUETA C.F C","escut":"00100_0000663994_guineueta_200x200.png","partits":7,"punts":0,"diff_gols":-89,"gols_afavor":0,"gols_encontra":89,"posicio":16}],"dataAcumulada":{"labels":["J1","J2","J3","J4","J5","J6","J7"],"datasets":[{"codequip":39914,"label":"SARRIÀ, C.P. C","data":[3,3,3,6,9,10,10],"fill":false,"lineTension":0.5,"pointBackgroundColor":"#fff","pointRadius":5,"borderColor":"#8dd3c7","pointBorderColor":"#8dd3c7"},{"codequip":39082,"label":"APA POBLE SEC, CE. A","data":[3,6,9,12,15,18,21],"fill":false,"lineTension":0.5,"pointBackgroundColor":"#fff","pointRadius":5,"borderColor":"#ffffb3","pointBorderColor":"#ffffb3"},{"codequip":44216155,"label":"Pª BARC. VILLAVERDE-PENITENTS C","data":[3,6,6,6,7,8,8],"fill":false,"lineTension":0.5,"pointBackgroundColor":"#fff","pointRadius":5,"borderColor":"#bebada","pointBorderColor":"#bebada"},{"codequip":36338,"label":"CATALÒNIA, U.B. D","data":[3,6,9,12,15,16,19],"fill":false,"lineTension":0.5,"pointBackgroundColor":"#fff","pointRadius":5,"borderColor":"#fb8072","pointBorderColor":"#fb8072"},{"codequip":34252,"label":"LA SALUT PERE GOL AE. B","data":[3,3,3,3,3,4,7],"fill":false,"lineTension":0.5,"pointBackgroundColor":"#fff","pointRadius":5,"borderColor":"#80b1d3","pointBorderColor":"#80b1d3"},{"codequip":40477,"label":"DON BOSCO, C.F. A","data":[1,1,1,1,2,5,8],"fill":false,"lineTension":0.5,"pointBackgroundColor":"#fff","pointRadius":5,"borderColor":"#fdb462","pointBorderColor":"#fdb462"},{"codequip":41973,"label":"PENYA BARC. COLLBLANC SANTS,AE A","data":[1,4,4,4,4,7,7],"fill":false,"lineTension":0.5,"pointBackgroundColor":"#fff","pointRadius":5,"borderColor":"#b3de69","pointBorderColor":"#b3de69"},{"codequip":37086,"label":"LLOREDA, C.F. A","data":[1,4,7,7,7,10,13],"fill":false,"lineTension":0.5,"pointBackgroundColor":"#fff","pointRadius":5,"borderColor":"#fccde5","pointBorderColor":"#fccde5"},{"codequip":33281582,"label":"DIAGONAL CLUB ESP. B","data":[1,4,7,10,13,16,16],"fill":false,"lineTension":0.5,"pointBackgroundColor":"#fff","pointRadius":5,"borderColor":"#d9d9d9","pointBorderColor":"#d9d9d9"},{"codequip":25560702,"label":"ESCOLA DE FUTBOL PREMIER BARCELONA D","data":[0,3,6,9,12,12,15],"fill":false,"lineTension":0.5,"pointBackgroundColor":"#fff","pointRadius":5,"borderColor":"#bc80bd","pointBorderColor":"#bc80bd"},{"codequip":31737402,"label":"POBLE NOU ,AT. C","data":[0,0,0,0,0,0,0],"fill":false,"lineTension":0.5,"pointBackgroundColor":"#fff","pointRadius":5,"borderColor":"#ccebc5","pointBorderColor":"#ccebc5"},{"codequip":34223,"label":"ESCOLA COLLBLANC-TORRASSA,C.E B","data":[0,0,0,3,6,6,6],"fill":false,"lineTension":0.5,"pointBackgroundColor":"#fff","pointRadius":5,"borderColor":"#ffed6f","pointBorderColor":"#ffed6f"},{"codequip":40746,"label":"UNIFICACION LLEFIA,CF. D","data":[0,0,0,0,0,0,0],"fill":false,"lineTension":0.5,"pointBackgroundColor":"#fff","pointRadius":5,"borderColor":"#8dd3c7","pointBorderColor":"#8dd3c7"},{"codequip":33923,"label":"MONTAÑESA, C.F. C","data":[0,0,3,3,3,3,3],"fill":false,"lineTension":0.5,"pointBackgroundColor":"#fff","pointRadius":5,"borderColor":"#ffffb3","pointBorderColor":"#ffffb3"},{"codequip":44173252,"label":"PADUA, ASSOC. CLUB B","data":[0,0,3,6,6,6,9],"fill":false,"lineTension":0.5,"pointBackgroundColor":"#fff","pointRadius":5,"borderColor":"#bebada","pointBorderColor":"#bebada"},{"codequip":36480387,"label":"ESCOLA ESPORTIVA GUINEUETA C.F C","data":[0,0,0,0,0,0,0],"fill":false,"lineTension":0.5,"pointBackgroundColor":"#fff","pointRadius":5,"borderColor":"#fb8072","pointBorderColor":"#fb8072"}]},"codgroup":"45056116","menuFollowTeams":[{"label":"Infantil A","href":"/classificacio?id=44295683"},{"label":"Infantil B","href":"/classificacio?id=45060446"},{"label":"Infantil C","href":"/classificacio?id=45056116"},{"label":"Infantil D","href":"/classificacio?id=45061389"}],"maxJornada":30,"jornada":7}