{"data":[{"codparticipant":36410137,"codgroup":45060446,"nom_jugador":"GUIFRÉ","any":2010,"codacta":3049924,"codequip":33638,"dorsal":11,"titular":1,"porter":null,"codequip_local":33638,"equip_local":"PARC, U.D. A","escut_local":"00100_0000763260_udparc_200x200.png","colorequipacio1_local":null,"codequip_visitant":40612,"equip_visitant":"POMAR, C.D. A","escut_visitant":"00100_0000902980_cdpomar_200.png","colorequipacio1_visitant":null,"jornada":3,"gols_local":6,"gols_visitant":1}],"dataGols":[],"codparticipant":"36410137","codequip":33638,"codgroup":45060446,"menuFollowTeams":[{"label":"Infantil A","href":"/classificacio?id=44295683"},{"label":"Infantil B","href":"/classificacio?id=45060446"},{"label":"Infantil C","href":"/classificacio?id=45056116"},{"label":"Infantil D","href":"/classificacio?id=45061389"}]}