{"data":[{"codacta":3047996,"jornada":1,"equip_casa":"ESCOLA DE FUTBOL PREMIER BARCELONA D","equip_fora":"POBLE NOU ,AT. C","gols_casa":"","gols_fora":"","codequip_casa":25560702,"codequip_fora":31737402,"estado":null,"escut_casa":"00100_0000754057_premierbcn_200x200.png","escut_fora":"00100_0000310887_Logo_Facebook.fw.png","data":"2022-10-09 16:30:00","estat":null,"nextFetch":"2022-10-09 05:30:00 PM","resultat":"nonplayeryet","nom_equip":"POBLE NOU ,AT. C"},{"codacta":3048004,"jornada":2,"equip_casa":"POBLE NOU ,AT. C","equip_fora":"ESCOLA COLLBLANC-TORRASSA,C.E B","gols_casa":"","gols_fora":"","codequip_casa":31737402,"codequip_fora":34223,"estado":null,"escut_casa":"00100_0000310887_Logo_Facebook.fw.png","escut_fora":"00100_0000003500_images.png","data":"2022-10-16 14:00:00","estat":null,"nextFetch":null,"resultat":"nonplayeryet","nom_equip":"POBLE NOU ,AT. C"},{"codacta":3048011,"jornada":3,"equip_casa":"UNIFICACION LLEFIA,CF. D","equip_fora":"POBLE NOU ,AT. C","gols_casa":"","gols_fora":"","codequip_casa":40746,"codequip_fora":31737402,"estado":null,"escut_casa":"00100_0000879078_llefia_200.png","escut_fora":"00100_0000310887_Logo_Facebook.fw.png","data":"2022-10-23 15:30:00","estat":null,"nextFetch":null,"resultat":"nonplayeryet","nom_equip":"POBLE NOU ,AT. C"},{"codacta":3048019,"jornada":4,"equip_casa":"POBLE NOU ,AT. C","equip_fora":"PENYA BARC. COLLBLANC SANTS,AE A","gols_casa":"","gols_fora":"","codequip_casa":31737402,"codequip_fora":41973,"estado":null,"escut_casa":"00100_0000310887_Logo_Facebook.fw.png","escut_fora":"00100_0000094725_Escudo3_1.png","data":"2022-10-30 14:00:00","estat":null,"nextFetch":null,"resultat":"nonplayeryet","nom_equip":"POBLE NOU ,AT. C"},{"codacta":3048026,"jornada":5,"equip_casa":"LLOREDA, C.F. A","equip_fora":"POBLE NOU ,AT. C","gols_casa":"","gols_fora":"","codequip_casa":37086,"codequip_fora":31737402,"estado":null,"escut_casa":"00100_0000897895_cflloreda_200.png","escut_fora":"00100_0000310887_Logo_Facebook.fw.png","data":"2022-11-05 14:30:00","estat":null,"nextFetch":null,"resultat":"nonplayeryet","nom_equip":"POBLE NOU ,AT. C"},{"codacta":3048034,"jornada":6,"equip_casa":"POBLE NOU ,AT. C","equip_fora":"PADUA, ASSOC. CLUB B","gols_casa":"","gols_fora":"","codequip_casa":31737402,"codequip_fora":44173252,"estado":null,"escut_casa":"00100_0000310887_Logo_Facebook.fw.png","escut_fora":"00100_0000813057_6570_Padua_200.png","data":"2022-11-13 14:00:00","estat":null,"nextFetch":null,"resultat":"nonplayeryet","nom_equip":"POBLE NOU ,AT. C"},{"codacta":3048041,"jornada":7,"equip_casa":"SARRIÀ, C.P. C","equip_fora":"POBLE NOU ,AT. C","gols_casa":"","gols_fora":"","codequip_casa":39914,"codequip_fora":31737402,"estado":null,"escut_casa":"00100_0000388904_00100_0000337753_escut-cp-sarria-1952.png","escut_fora":"00100_0000310887_Logo_Facebook.fw.png","data":"2022-11-19 14:30:00","estat":null,"nextFetch":null,"resultat":"nonplayeryet","nom_equip":"POBLE NOU ,AT. C"},{"codacta":3048049,"jornada":8,"equip_casa":"POBLE NOU ,AT. C","equip_fora":"Pª BARC. VILLAVERDE-PENITENTS C","gols_casa":"","gols_fora":"","codequip_casa":31737402,"codequip_fora":44216155,"estado":null,"escut_casa":"00100_0000310887_Logo_Facebook.fw.png","escut_fora":"00100_0000012218_Villaverde pequeno.png","data":"2022-11-27 14:00:00","estat":null,"nextFetch":null,"resultat":"nonplayeryet","nom_equip":"POBLE NOU ,AT. C"},{"codacta":3048056,"jornada":9,"equip_casa":"MONTAÑESA, C.F. C","equip_fora":"POBLE NOU ,AT. C","gols_casa":"","gols_fora":"","codequip_casa":33923,"codequip_fora":31737402,"estado":null,"escut_casa":"00100_0000584781_montanesa_200x200.png","escut_fora":"00100_0000310887_Logo_Facebook.fw.png","data":"2022-12-11 16:00:00","estat":null,"nextFetch":null,"resultat":"nonplayeryet","nom_equip":"POBLE NOU ,AT. C"},{"codacta":3048064,"jornada":10,"equip_casa":"POBLE NOU ,AT. C","equip_fora":"ESCOLA ESPORTIVA GUINEUETA C.F C","gols_casa":"","gols_fora":"","codequip_casa":31737402,"codequip_fora":36480387,"estado":null,"escut_casa":"00100_0000310887_Logo_Facebook.fw.png","escut_fora":"00100_0000663994_guineueta_200x200.png","data":"2022-12-18 14:00:00","estat":null,"nextFetch":null,"resultat":"nonplayeryet","nom_equip":"POBLE NOU ,AT. C"},{"codacta":3048071,"jornada":11,"equip_casa":"APA POBLE SEC, CE. A","equip_fora":"POBLE NOU ,AT. C","gols_casa":"","gols_fora":"","codequip_casa":39082,"codequip_fora":31737402,"estado":null,"escut_casa":"00100_0000287980_Escut_2D_-_66px_-_fons_transparent.png","escut_fora":"00100_0000310887_Logo_Facebook.fw.png","data":"2023-01-07 12:00:00","estat":null,"nextFetch":null,"resultat":"nonplayeryet","nom_equip":"POBLE NOU ,AT. C"},{"codacta":3048079,"jornada":12,"equip_casa":"POBLE NOU ,AT. C","equip_fora":"DIAGONAL CLUB ESP. B","gols_casa":"","gols_fora":"","codequip_casa":31737402,"codequip_fora":33281582,"estado":null,"escut_casa":"00100_0000310887_Logo_Facebook.fw.png","escut_fora":"00100_0000484899_DIAGONAL_CLUB_ESPORTIU_copia.png","data":"2023-01-15 14:00:00","estat":null,"nextFetch":null,"resultat":"nonplayeryet","nom_equip":"POBLE NOU ,AT. C"},{"codacta":3048086,"jornada":13,"equip_casa":"DON BOSCO, C.F. A","equip_fora":"POBLE NOU ,AT. C","gols_casa":"","gols_fora":"","codequip_casa":40477,"codequip_fora":31737402,"estado":null,"escut_casa":"00100_0000105692_bosco.png","escut_fora":"00100_0000310887_Logo_Facebook.fw.png","data":"2023-01-22 09:45:00","estat":null,"nextFetch":null,"resultat":"nonplayeryet","nom_equip":"POBLE NOU ,AT. C"},{"codacta":3048094,"jornada":14,"equip_casa":"POBLE NOU ,AT. C","equip_fora":"LA SALUT PERE GOL AE. B","gols_casa":"","gols_fora":"","codequip_casa":31737402,"codequip_fora":34252,"estado":null,"escut_casa":"00100_0000310887_Logo_Facebook.fw.png","escut_fora":"00100_0000651347_lasalutperegol_200x200.png","data":"2023-01-29 14:00:00","estat":null,"nextFetch":null,"resultat":"nonplayeryet","nom_equip":"POBLE NOU ,AT. C"},{"codacta":3048101,"jornada":15,"equip_casa":"CATALÒNIA, U.B. D","equip_fora":"POBLE NOU ,AT. C","gols_casa":"","gols_fora":"","codequip_casa":36338,"codequip_fora":31737402,"estado":null,"escut_casa":"00100_0000675978_catalonia_200x200.png","escut_fora":"00100_0000310887_Logo_Facebook.fw.png","data":"2023-02-05 14:15:00","estat":null,"nextFetch":null,"resultat":"nonplayeryet","nom_equip":"POBLE NOU ,AT. C"},{"codacta":3048116,"jornada":16,"equip_casa":"POBLE NOU ,AT. C","equip_fora":"ESCOLA DE FUTBOL PREMIER BARCELONA D","gols_casa":"","gols_fora":"","codequip_casa":31737402,"codequip_fora":25560702,"estado":null,"escut_casa":"00100_0000310887_Logo_Facebook.fw.png","escut_fora":"00100_0000754057_premierbcn_200x200.png","data":"2023-02-12 14:00:00","estat":null,"nextFetch":null,"resultat":"nonplayeryet","nom_equip":"POBLE NOU ,AT. C"},{"codacta":3048124,"jornada":17,"equip_casa":"ESCOLA COLLBLANC-TORRASSA,C.E B","equip_fora":"POBLE NOU ,AT. C","gols_casa":"","gols_fora":"","codequip_casa":34223,"codequip_fora":31737402,"estado":null,"escut_casa":"00100_0000003500_images.png","escut_fora":"00100_0000310887_Logo_Facebook.fw.png","data":"2023-02-26 10:00:00","estat":null,"nextFetch":null,"resultat":"nonplayeryet","nom_equip":"POBLE NOU ,AT. C"},{"codacta":3048131,"jornada":18,"equip_casa":"POBLE NOU ,AT. C","equip_fora":"UNIFICACION LLEFIA,CF. D","gols_casa":"","gols_fora":"","codequip_casa":31737402,"codequip_fora":40746,"estado":null,"escut_casa":"00100_0000310887_Logo_Facebook.fw.png","escut_fora":"00100_0000879078_llefia_200.png","data":"2023-03-05 14:00:00","estat":null,"nextFetch":null,"resultat":"nonplayeryet","nom_equip":"POBLE NOU ,AT. C"},{"codacta":3048139,"jornada":19,"equip_casa":"PENYA BARC. COLLBLANC SANTS,AE A","equip_fora":"POBLE NOU ,AT. C","gols_casa":"","gols_fora":"","codequip_casa":41973,"codequip_fora":31737402,"estado":null,"escut_casa":"00100_0000094725_Escudo3_1.png","escut_fora":"00100_0000310887_Logo_Facebook.fw.png","data":"2023-03-12 15:15:00","estat":null,"nextFetch":null,"resultat":"nonplayeryet","nom_equip":"POBLE NOU ,AT. C"},{"codacta":3048146,"jornada":20,"equip_casa":"POBLE NOU ,AT. C","equip_fora":"LLOREDA, C.F. A","gols_casa":"","gols_fora":"","codequip_casa":31737402,"codequip_fora":37086,"estado":null,"escut_casa":"00100_0000310887_Logo_Facebook.fw.png","escut_fora":"00100_0000897895_cflloreda_200.png","data":"2023-03-19 14:00:00","estat":null,"nextFetch":null,"resultat":"nonplayeryet","nom_equip":"POBLE NOU ,AT. C"},{"codacta":3048154,"jornada":21,"equip_casa":"PADUA, ASSOC. CLUB B","equip_fora":"POBLE NOU ,AT. C","gols_casa":"","gols_fora":"","codequip_casa":44173252,"codequip_fora":31737402,"estado":null,"escut_casa":"00100_0000813057_6570_Padua_200.png","escut_fora":"00100_0000310887_Logo_Facebook.fw.png","data":"2023-03-25 13:30:00","estat":null,"nextFetch":null,"resultat":"nonplayeryet","nom_equip":"POBLE NOU ,AT. C"},{"codacta":3048161,"jornada":22,"equip_casa":"POBLE NOU ,AT. C","equip_fora":"SARRIÀ, C.P. C","gols_casa":"","gols_fora":"","codequip_casa":31737402,"codequip_fora":39914,"estado":null,"escut_casa":"00100_0000310887_Logo_Facebook.fw.png","escut_fora":"00100_0000388904_00100_0000337753_escut-cp-sarria-1952.png","data":"2023-04-02 14:00:00","estat":null,"nextFetch":null,"resultat":"nonplayeryet","nom_equip":"POBLE NOU ,AT. C"},{"codacta":3048169,"jornada":23,"equip_casa":"Pª BARC. VILLAVERDE-PENITENTS C","equip_fora":"POBLE NOU ,AT. C","gols_casa":"","gols_fora":"","codequip_casa":44216155,"codequip_fora":31737402,"estado":null,"escut_casa":"00100_0000012218_Villaverde pequeno.png","escut_fora":"00100_0000310887_Logo_Facebook.fw.png","data":"2023-04-16 10:00:00","estat":null,"nextFetch":null,"resultat":"nonplayeryet","nom_equip":"POBLE NOU ,AT. C"},{"codacta":3048176,"jornada":24,"equip_casa":"POBLE NOU ,AT. C","equip_fora":"MONTAÑESA, C.F. C","gols_casa":"","gols_fora":"","codequip_casa":31737402,"codequip_fora":33923,"estado":null,"escut_casa":"00100_0000310887_Logo_Facebook.fw.png","escut_fora":"00100_0000584781_montanesa_200x200.png","data":"2023-04-23 14:00:00","estat":null,"nextFetch":null,"resultat":"nonplayeryet","nom_equip":"POBLE NOU ,AT. C"},{"codacta":3048184,"jornada":25,"equip_casa":"ESCOLA ESPORTIVA GUINEUETA C.F C","equip_fora":"POBLE NOU ,AT. C","gols_casa":"","gols_fora":"","codequip_casa":36480387,"codequip_fora":31737402,"estado":null,"escut_casa":"00100_0000663994_guineueta_200x200.png","escut_fora":"00100_0000310887_Logo_Facebook.fw.png","data":"2023-04-29 14:30:00","estat":null,"nextFetch":null,"resultat":"nonplayeryet","nom_equip":"POBLE NOU ,AT. C"},{"codacta":3048191,"jornada":26,"equip_casa":"POBLE NOU ,AT. C","equip_fora":"APA POBLE SEC, CE. A","gols_casa":"","gols_fora":"","codequip_casa":31737402,"codequip_fora":39082,"estado":null,"escut_casa":"00100_0000310887_Logo_Facebook.fw.png","escut_fora":"00100_0000287980_Escut_2D_-_66px_-_fons_transparent.png","data":"2023-05-07 14:00:00","estat":null,"nextFetch":null,"resultat":"nonplayeryet","nom_equip":"POBLE NOU ,AT. C"},{"codacta":3048199,"jornada":27,"equip_casa":"DIAGONAL CLUB ESP. B","equip_fora":"POBLE NOU ,AT. C","gols_casa":"","gols_fora":"","codequip_casa":33281582,"codequip_fora":31737402,"estado":null,"escut_casa":"00100_0000484899_DIAGONAL_CLUB_ESPORTIU_copia.png","escut_fora":"00100_0000310887_Logo_Facebook.fw.png","data":"2023-05-13 11:45:00","estat":null,"nextFetch":null,"resultat":"nonplayeryet","nom_equip":"POBLE NOU ,AT. C"},{"codacta":3048206,"jornada":28,"equip_casa":"POBLE NOU ,AT. C","equip_fora":"DON BOSCO, C.F. A","gols_casa":"","gols_fora":"","codequip_casa":31737402,"codequip_fora":40477,"estado":null,"escut_casa":"00100_0000310887_Logo_Facebook.fw.png","escut_fora":"00100_0000105692_bosco.png","data":"2023-05-21 14:00:00","estat":null,"nextFetch":null,"resultat":"nonplayeryet","nom_equip":"POBLE NOU ,AT. C"},{"codacta":3048214,"jornada":29,"equip_casa":"LA SALUT PERE GOL AE. B","equip_fora":"POBLE NOU ,AT. C","gols_casa":"","gols_fora":"","codequip_casa":34252,"codequip_fora":31737402,"estado":null,"escut_casa":"00100_0000651347_lasalutperegol_200x200.png","escut_fora":"00100_0000310887_Logo_Facebook.fw.png","data":"2023-05-27 13:15:00","estat":null,"nextFetch":null,"resultat":"nonplayeryet","nom_equip":"POBLE NOU ,AT. C"},{"codacta":3048221,"jornada":30,"equip_casa":"POBLE NOU ,AT. C","equip_fora":"CATALÒNIA, U.B. D","gols_casa":"","gols_fora":"","codequip_casa":31737402,"codequip_fora":36338,"estado":null,"escut_casa":"00100_0000310887_Logo_Facebook.fw.png","escut_fora":"00100_0000675978_catalonia_200x200.png","data":"2023-06-04 14:00:00","estat":null,"nextFetch":null,"resultat":"nonplayeryet","nom_equip":"POBLE NOU ,AT. C"}],"codequip":"31737402","codgroup":"45056116","dataAcumulada":{"labels":["J1","J2","J3","J4","J5","J6","J7","J8","J9","J10","J11","J12","J13","J14","J15","J16","J17","J18","J19","J20","J21","J22","J23","J24","J25","J26","J27","J28","J29","J30"],"datasets":[{"codequip":31737402,"label":"POBLE NOU ,AT. C","data":[0,0,0,0,0,0,0,0,0,0,0,0,0,0,0,0,0,0,0,0,0,0,0,0,0,0,0,0,0,0],"fill":false,"lineTension":0.5,"pointBackgroundColor":"#fff","pointRadius":5,"borderColor":"#8dd3c7","pointBorderColor":"#8dd3c7"}]},"menuFollowTeams":[{"label":"Infantil A","href":"/classificacio?id=44295683"},{"label":"Infantil B","href":"/classificacio?id=45060446"},{"label":"Infantil C","href":"/classificacio?id=45056116"},{"label":"Infantil D","href":"/classificacio?id=45061389"}]}