{"data":[{"codparticipant":46002891,"nom_jugador":"EDUARDO","dorsal":25,"any":2009,"codequip":33281582,"nom_equip":"DIAGONAL CLUB ESP. B","escut":"00100_0000484899_DIAGONAL_CLUB_ESPORTIU_copia.png","tipus":"normal","gols":35},{"codparticipant":45192603,"nom_jugador":"ORIOL","dorsal":8,"any":2010,"codequip":33281582,"nom_equip":"DIAGONAL CLUB ESP. B","escut":"00100_0000484899_DIAGONAL_CLUB_ESPORTIU_copia.png","tipus":"normal","gols":22},{"codparticipant":39931383,"nom_jugador":"LOUIS WALTER","dorsal":9,"any":2010,"codequip":33281582,"nom_equip":"DIAGONAL CLUB ESP. B","escut":"00100_0000484899_DIAGONAL_CLUB_ESPORTIU_copia.png","tipus":"normal","gols":13},{"codparticipant":46018507,"nom_jugador":"MAX","dorsal":24,"any":2009,"codequip":33281582,"nom_equip":"DIAGONAL CLUB ESP. B","escut":"00100_0000484899_DIAGONAL_CLUB_ESPORTIU_copia.png","tipus":"normal","gols":12},{"codparticipant":45317484,"nom_jugador":"MARC","dorsal":4,"any":2010,"codequip":33281582,"nom_equip":"DIAGONAL CLUB ESP. B","escut":"00100_0000484899_DIAGONAL_CLUB_ESPORTIU_copia.png","tipus":"normal","gols":10},{"codparticipant":45192796,"nom_jugador":"GUILLE CHACÓN","dorsal":21,"any":2010,"codequip":33281582,"nom_equip":"DIAGONAL CLUB ESP. B","escut":"00100_0000484899_DIAGONAL_CLUB_ESPORTIU_copia.png","tipus":"normal","gols":7},{"codparticipant":45153128,"nom_jugador":"LLUC","dorsal":12,"any":2009,"codequip":33281582,"nom_equip":"DIAGONAL CLUB ESP. B","escut":"00100_0000484899_DIAGONAL_CLUB_ESPORTIU_copia.png","tipus":"normal","gols":6},{"codparticipant":35582712,"nom_jugador":"POL","dorsal":10,"any":2010,"codequip":33281582,"nom_equip":"DIAGONAL CLUB ESP. B","escut":"00100_0000484899_DIAGONAL_CLUB_ESPORTIU_copia.png","tipus":"normal","gols":5},{"codparticipant":46029574,"nom_jugador":"FERNANDO","dorsal":18,"any":2009,"codequip":33281582,"nom_equip":"DIAGONAL CLUB ESP. B","escut":"00100_0000484899_DIAGONAL_CLUB_ESPORTIU_copia.png","tipus":"normal","gols":4},{"codparticipant":45192856,"nom_jugador":"BRUNO","dorsal":17,"any":2009,"codequip":33281582,"nom_equip":"DIAGONAL CLUB ESP. B","escut":"00100_0000484899_DIAGONAL_CLUB_ESPORTIU_copia.png","tipus":"normal","gols":4},{"codparticipant":43799703,"nom_jugador":"ALEXANDER","dorsal":11,"any":2009,"codequip":33281582,"nom_equip":"DIAGONAL CLUB ESP. B","escut":"00100_0000484899_DIAGONAL_CLUB_ESPORTIU_copia.png","tipus":"normal","gols":4},{"codparticipant":38848103,"nom_jugador":"FRANCESC","dorsal":7,"any":2010,"codequip":33281582,"nom_equip":"DIAGONAL CLUB ESP. B","escut":"00100_0000484899_DIAGONAL_CLUB_ESPORTIU_copia.png","tipus":"normal","gols":3},{"codparticipant":43448340,"nom_jugador":"PHILEMON LOUIS GUY","dorsal":20,"any":2010,"codequip":33281582,"nom_equip":"DIAGONAL CLUB ESP. B","escut":"00100_0000484899_DIAGONAL_CLUB_ESPORTIU_copia.png","tipus":"normal","gols":2},{"codparticipant":42543796,"nom_jugador":"MAURO","dorsal":76,"any":2009,"codequip":33281582,"nom_equip":"DIAGONAL CLUB ESP. B","escut":"00100_0000484899_DIAGONAL_CLUB_ESPORTIU_copia.png","tipus":"normal","gols":2},{"codparticipant":38845528,"nom_jugador":"GABRIEL","dorsal":14,"any":2010,"codequip":33281582,"nom_equip":"DIAGONAL CLUB ESP. B","escut":"00100_0000484899_DIAGONAL_CLUB_ESPORTIU_copia.png","tipus":"normal","gols":2},{"codparticipant":33926344,"nom_jugador":"JORDI","dorsal":16,"any":2010,"codequip":33281582,"nom_equip":"DIAGONAL CLUB ESP. B","escut":"00100_0000484899_DIAGONAL_CLUB_ESPORTIU_copia.png","tipus":"normal","gols":2},{"codparticipant":28548971,"nom_jugador":"PAU","dorsal":3,"any":2010,"codequip":33281582,"nom_equip":"DIAGONAL CLUB ESP. B","escut":"00100_0000484899_DIAGONAL_CLUB_ESPORTIU_copia.png","tipus":"normal","gols":2},{"codparticipant":45317534,"nom_jugador":"DANIEL","dorsal":47,"any":2009,"codequip":33281582,"nom_equip":"DIAGONAL CLUB ESP. B","escut":"00100_0000484899_DIAGONAL_CLUB_ESPORTIU_copia.png","tipus":"normal","gols":1},{"codparticipant":38845021,"nom_jugador":"MAX","dorsal":6,"any":2010,"codequip":33281582,"nom_equip":"DIAGONAL CLUB ESP. B","escut":"00100_0000484899_DIAGONAL_CLUB_ESPORTIU_copia.png","tipus":"normal","gols":1}],"codgroup":"45056116","codequip":"33281582","menuFollowTeams":[{"label":"Infantil A","href":"/classificacio?id=44295683"},{"label":"Infantil B","href":"/classificacio?id=45060446"},{"label":"Infantil C","href":"/classificacio?id=45056116"},{"label":"Infantil D","href":"/classificacio?id=45061389"}]}